os_traits/__init__.py
os_traits/compute/__init__.py
os_traits/compute/arch.py
os_traits/compute/config_drive.py
os_traits/compute/ephemeral.py
os_traits/compute/firmware.py
os_traits/compute/graphics.py
os_traits/compute/image.py
os_traits/compute/migrate.py
os_traits/compute/net.py
os_traits/compute/security.py
os_traits/compute/sound.py
os_traits/compute/status.py
os_traits/compute/storage.py
os_traits/compute/usb.py
os_traits/compute/viommu.py
os_traits/compute/volume.py
os_traits/hw/__init__.py
os_traits/hw/arch.py
os_traits/hw/cpu/__init__.py
os_traits/hw/cpu/aarch64.py
os_traits/hw/cpu/amd.py
os_traits/hw/cpu/ppc64le/__init__.py
os_traits/hw/cpu/x86/__init__.py
os_traits/hw/cpu/x86/amd.py
os_traits/hw/cpu/x86/intel.py
os_traits/hw/gpu/__init__.py
os_traits/hw/gpu/api.py
os_traits/hw/gpu/cuda.py
os_traits/hw/gpu/max_display_heads.py
os_traits/hw/gpu/resolution.py
os_traits/hw/nic/__init__.py
os_traits/hw/nic/accel.py
os_traits/hw/nic/dcb.py
os_traits/hw/nic/offload.py
os_traits/hw/nic/sriov.py
os_traits/hw/numa/__init__.py
os_traits/hw/pci/__init__.py
os_traits/misc/__init__.py
os_traits/owner/__init__.py
os_traits/storage/__init__.py
os_traits/storage/disk.py
os_traits/tests/__init__.py
os_traits/tests/base.py
os_traits/tests/test_cuda.py
os_traits/tests/test_os_traits.py
os_traits-3.5.0.dist-info/AUTHORS
os_traits-3.5.0.dist-info/LICENSE
os_traits-3.5.0.dist-info/METADATA
os_traits-3.5.0.dist-info/WHEEL
os_traits-3.5.0.dist-info/pbr.json
os_traits-3.5.0.dist-info/top_level.txt
os_traits-3.5.0.dist-info/RECORD
